temporal_activity_cache/__init__.py
temporal_activity_cache/backends/__init__.py
temporal_activity_cache/backends/base.py
temporal_activity_cache/backends/redis.py
temporal_activity_cache/cache.py
temporal_activity_cache/enums.py
temporal_activity_cache/py.typed
temporal_activity_cache/utils.py
temporal_activity_cache-0.3.0.dist-info/WHEEL
temporal_activity_cache-0.3.0.dist-info/METADATA
temporal_activity_cache-0.3.0.dist-info/RECORD
