Metadata-Version: 2.3
Name: temporal-activity-cache
Version: 0.3.0
Summary: Prefect-style activity caching for Temporal workflows using Redis
Keywords: temporal,cache,redis,workflow,activity
License: MIT
Classifier: Development Status :: 3 - Alpha
Classifier: Intended Audience :: Developers
Classifier: License :: OSI Approved :: MIT License
Classifier: Programming Language :: Python :: 3
Classifier: Programming Language :: Python :: 3.10
Classifier: Programming Language :: Python :: 3.11
Classifier: Programming Language :: Python :: 3.12
Classifier: Topic :: Software Development :: Libraries :: Python Modules
Requires-Dist: temporalio>=1.8.0
Requires-Dist: redis[hiredis]>=5.0.0
Requires-Dist: pydantic>=2.0.0
Requires-Python: >=3.10
Project-URL: Documentation, https://github.com/huscarldev/temporal-activity-cache#readme
Project-URL: Homepage, https://github.com/huscarldev/temporal-activity-cache
Project-URL: Issues, https://github.com/huscarldev/temporal-activity-cache/issues
Project-URL: Repository, https://github.com/huscarldev/temporal-activity-cache
